git_fzf_more/__init__.py
git_fzf_more/irm.py
git_fzf_more-1.0.1.dist-info/METADATA
git_fzf_more-1.0.1.dist-info/WHEEL
git_fzf_more-1.0.1.dist-info/entry_points.txt
git_fzf_more-1.0.1.dist-info/top_level.txt
git_fzf_more-1.0.1.dist-info/RECORD
